molecule_lima/__init__.py
molecule_lima/driver.py
molecule_lima/playbooks/create.yml
molecule_lima/playbooks/create_instance.yml
molecule_lima/playbooks/destroy.yml
molecule_lima/playbooks/prepare.yml
molecule_lima/playbooks/validate_instance.yml
molecule_lima-0.0.3.dist-info/licenses/LICENSE
molecule_lima-0.0.3.dist-info/METADATA
molecule_lima-0.0.3.dist-info/WHEEL
molecule_lima-0.0.3.dist-info/entry_points.txt
molecule_lima-0.0.3.dist-info/top_level.txt
molecule_lima-0.0.3.dist-info/RECORD
