Metadata-Version: 2.4
Name: molecule-lima
Version: 0.0.3
Summary: Molecule driver for Lima VM - Test Ansible roles on macOS Apple Silicon and Linux
Author-email: Ivan Filatof <filatof@gmail.com>
Maintainer-email: Ivan Filatof <filatof@gmail.com>
License: MIT
Project-URL: Homepage, https://github.com/filatof/molecule-lima
Project-URL: Documentation, https://github.com/filatof/molecule-lima#readme
Project-URL: Repository, https://github.com/filatof/molecule-lima
Project-URL: Issues, https://github.com/filatof/molecule-lima/issues
Project-URL: Changelog, https://github.com/filatof/molecule-lima/blob/main/CHANGELOG.md
Keywords: ansible,molecule,testing,lima,virtualization,macos,apple-silicon,arm64
Classifier: Development Status :: 4 - Beta
Classifier: Intended Audience :: Developers
Classifier: License :: OSI Approved :: MIT License
Classifier: Operating System :: MacOS
Classifier: Operating System :: POSIX :: Linux
Classifier: Programming Language :: Python :: 3
Classifier: Programming Language :: Python :: 3.9
Classifier: Programming Language :: Python :: 3.10
Classifier: Programming Language :: Python :: 3.11
Classifier: Programming Language :: Python :: 3.12
Classifier: Programming Language :: Python :: 3.13
Classifier: Topic :: Software Development :: Testing
Classifier: Topic :: System :: Systems Administration
Classifier: Topic :: Utilities
Requires-Python: >=3.9
License-File: LICENSE
Requires-Dist: molecule>=6.0.0
Requires-Dist: ansible-core>=2.12.0
Requires-Dist: pyyaml>=5.1
Requires-Dist: jinja2>=2.11.3
Provides-Extra: dev
Requires-Dist: pytest>=7.0; extra == "dev"
Requires-Dist: pytest-cov>=4.0; extra == "dev"
Requires-Dist: pytest-mock>=3.10; extra == "dev"
Requires-Dist: black>=23.0; extra == "dev"
Requires-Dist: ruff>=0.1.0; extra == "dev"
Requires-Dist: mypy>=1.0; extra == "dev"
Requires-Dist: pre-commit>=3.0; extra == "dev"
Provides-Extra: docs
Requires-Dist: mkdocs>=1.5; extra == "docs"
Requires-Dist: mkdocs-material>=9.0; extra == "docs"
Dynamic: license-file
